categorical_encoding/__init__.py
categorical_encoding/encoders/__init__.py
categorical_encoding/encoders/encoder.py
categorical_encoding/encoders/encoder_methods/__init__.py
categorical_encoding/encoders/encoder_methods/binary_encoder.py
categorical_encoding/encoders/encoder_methods/hashing_encoder.py
categorical_encoding/encoders/encoder_methods/leave_one_out_encoder.py
categorical_encoding/encoders/encoder_methods/one_hot_encoder.py
categorical_encoding/encoders/encoder_methods/ordinal_encoder.py
categorical_encoding/encoders/encoder_methods/target_encoder.py
categorical_encoding/primitives/__init__.py
categorical_encoding/primitives/binary_enc.py
categorical_encoding/primitives/hashing_enc.py
categorical_encoding/primitives/leave_one_out_enc.py
categorical_encoding/primitives/one_hot_enc.py
categorical_encoding/primitives/ordinal_enc.py
categorical_encoding/primitives/target_enc.py
categorical_encoding/tests/__init__.py
categorical_encoding/tests/test_encoding.py
categorical_encoding/tests/testing_utils.py
categorical_encoding-0.4.1.dist-info/LICENSE
categorical_encoding-0.4.1.dist-info/METADATA
categorical_encoding-0.4.1.dist-info/WHEEL
categorical_encoding-0.4.1.dist-info/top_level.txt
categorical_encoding-0.4.1.dist-info/RECORD
