Metadata-Version: 2.1
Name: categorical-encoding
Version: 0.4.1
Summary: categorical encoding for featuretools
Home-page: http://www.featurelabs.com/
Author: Feature Labs, Inc.
Author-email: support@featurelabs.com
License: BSD 3-clause
Keywords: feature engineering data science machine learning categorical encoding
Platform: UNKNOWN
Requires-Dist: featuretools (>=0.9.0)
Requires-Dist: category-encoders (==2.0.0)
